odoo8_addon_shopinvader_visible_discount-8.0.1.0.0.99.dev1-py3.8-nspkg.pth
odoo_addons/shopinvader_visible_discount/README.rst
odoo_addons/shopinvader_visible_discount/__init__.py
odoo_addons/shopinvader_visible_discount/__openerp__.py
odoo_addons/shopinvader_visible_discount/hooks.py
odoo_addons/shopinvader_visible_discount/models/__init__.py
odoo_addons/shopinvader_visible_discount/models/product.py
odoo_addons/shopinvader_visible_discount/tests/__init__.py
odoo_addons/shopinvader_visible_discount/tests/test_product.py
odoo8_addon_shopinvader_visible_discount-8.0.1.0.0.99.dev1.dist-info/METADATA
odoo8_addon_shopinvader_visible_discount-8.0.1.0.0.99.dev1.dist-info/WHEEL
odoo8_addon_shopinvader_visible_discount-8.0.1.0.0.99.dev1.dist-info/namespace_packages.txt
odoo8_addon_shopinvader_visible_discount-8.0.1.0.0.99.dev1.dist-info/top_level.txt
odoo8_addon_shopinvader_visible_discount-8.0.1.0.0.99.dev1.dist-info/RECORD
